{
  "events": [
    {
      "title": "gfsd",
      "description": "gfsd",
      "category": 3,
      "start": "2021-09-17T00:00:00.000Z",
      "done": false,
      "priroty": 2021081908,
      "id": 3,
      "end": null
    },
    {
      "title": "hgfd",
      "description": "hgfd",
      "category": 4,
      "start": "2021-09-17T00:00:00.000Z",
      "done": true,
      "priroty": 2021081901,
      "id": 4,
      "end": "2021-09-18T15:46:42.319Z"
    },
    {
      "title": "hgfd",
      "description": "hgfd",
      "start": "2021-09-17T00:00:00.000Z",
      "done": true,
      "priroty": 2021081806,
      "id": 5,
      "end": "2021-09-17T20:24:41.250Z"
    },
    {
      "category": 3,
      "title": "fd",
      "description": "dfgd",
      "start": "2021-09-17T00:00:00.000Z",
      "done": true,
      "priroty": 2021081903,
      "id": 6,
      "end": "2021-09-18T19:56:36.095Z"
    },
    {
      "title": "rwe",
      "description": "gr",
      "category": 1,
      "start": "2021-09-18T00:00:00.000Z",
      "done": true,
      "priroty": 2021081900,
      "id": 7,
      "end": "2021-09-18T16:04:15.118Z"
    },
    {
      "title": "kghu",
      "description": "kjh",
      "start": "2021-09-17T00:00:00.000Z",
      "done": true,
      "priroty": 2021081904,
      "id": 8,
      "end": "2021-09-18T19:56:37.753Z"
    },
    {
      "title": "kjgh",
      "description": "kjhg",
      "start": "2021-09-17T00:00:00.000Z",
      "done": true,
      "priroty": 2021081905,
      "id": 9,
      "end": "2021-09-18T19:56:36.930Z"
    },
    {
      "title": "adsfaadsfa",
      "description": "dasf",
      "category": 2,
      "start": "2021-09-24T00:00:00.000Z",
      "done": false,
      "priroty": 2021081806,
      "id": 10
    },
    {
      "title": 111,
      "description": 111,
      "category": 2,
      "start": "2021-09-21T00:00:00.000Z",
      "done": false,
      "priroty": 2021081807,
      "id": 11,
      "end": null
    },
    {
      "title": 111,
      "description": 111,
      "category": 2,
      "start": "2021-09-18T00:00:00.000Z",
      "done": true,
      "priroty": 2021081902,
      "id": 12,
      "end": "2021-09-19T16:55:23.810Z"
    },
    {
      "title": "asdfasdfasdfadsf",
      "description": "adsf",
      "category": 1,
      "start": "2021-09-13T00:00:00.000Z",
      "done": false,
      "priroty": 2021081909,
      "id": 13
    },
    {
      "title": "bewerbung schreiben",
      "description": "gfds\nGFDS\nGFDS\ngfds",
      "category": 1,
      "start": "2021-09-19T00:00:00.000Z",
      "done": false,
      "priroty": 2021081911,
      "id": 14
    },
    {
      "title": "gfds",
      "description": "gfdsgfds",
      "category": 2,
      "start": "2021-09-19T00:00:00.000Z",
      "done": false,
      "priroty": 2021081912,
      "id": 15
    },
    {
      "title": "gfdsgfds",
      "description": "gfdsgfds",
      "category": 3,
      "start": "2021-09-19T00:00:00.000Z",
      "done": false,
      "priroty": 2021081913,
      "id": 16
    },
    {
      "title": "Kochen",
      "description": "fds",
      "start": "2021-09-18T00:00:00.000Z",
      "done": false,
      "priroty": 2021081901,
      "id": 17,
      "end": null,
      "category": 5
    },
    {
      "title": "Küche sauber machen",
      "description": "fdsa",
      "category": 1,
      "start": "2021-09-18T00:00:00.000Z",
      "done": false,
      "priroty": 2021081902,
      "id": 18,
      "end": null
    },
    {
      "title": "Bewerbung schreiben",
      "description": "gfdsd",
      "category": 5,
      "start": "2021-09-18T00:00:00.000Z",
      "done": false,
      "priroty": 2021081900,
      "id": 19,
      "end": null
    },
    {
      "title": "jhgjhg",
      "description": "jhgfjhg",
      "category": 1,
      "start": "2021-09-01T00:00:00.000Z",
      "done": false,
      "priroty": 2021081904,
      "id": 20
    },
    {
      "title": "jhgfj",
      "description": "jhgfjhg",
      "category": 1,
      "start": "2021-09-01T00:00:00.000Z",
      "done": false,
      "priroty": 2021081903,
      "id": 21
    },
    {
      "title": "jhgfjhgf",
      "description": "jhgfjhgf",
      "category": 1,
      "start": "2021-09-01T00:00:00.000Z",
      "done": false,
      "priroty": 2021081905,
      "id": 22
    },
    {
      "title": "jhgfjhgfjgfh",
      "description": "jhgfjhgf",
      "category": 1,
      "start": "2021-09-01T00:00:00.000Z",
      "done": false,
      "priroty": 2021081906,
      "id": 23
    },
    {
      "title": "hgfjgf",
      "description": "jhfgj",
      "category": 1,
      "start": "2021-09-01T00:00:00.000Z",
      "done": false,
      "priroty": 2021081907,
      "id": 24
    },
    {
      "description": "ads",
      "title": "adsf",
      "start": "2021-09-18T00:00:00.000Z",
      "done": false,
      "priroty": 2021081910,
      "id": 25
    }
  ],
  "categories": [
    {
      "category": "Master1",
      "color": "#6b906a",
      "id": 1
    },
    {
      "category": "Master - First",
      "color": "#ee4646",
      "id": 2
    },
    {
      "category": "Stefan",
      "color": "#72ba35",
      "id": 3
    },
    {
      "category": "z5tre",
      "color": "#f23b3b",
      "id": 4
    },
    {
      "category": "Haushalt",
      "color": "#67e3d8",
      "id": 5
    }
  ],
  "timer-configuration": [
    {
      "id": 1,
      "interval": 5,
      "smallBreak": 2,
      "bigBreak": 3,
      "intervalCount": 2
    }
  ],
  "statistic_day": [
    {
      "sum": 5,
      "date": "2021-09-19T00:00:00.000Z",
      "statisticPerCategory": [
        {
          "id": 5,
          "count": 5
        }
      ],
      "id": 1
    }
  ]
}